prediction.py
img_prediction-0.0.6.dist-info/LICENSE
img_prediction-0.0.6.dist-info/METADATA
img_prediction-0.0.6.dist-info/WHEEL
img_prediction-0.0.6.dist-info/entry_points.txt
img_prediction-0.0.6.dist-info/top_level.txt
img_prediction-0.0.6.dist-info/RECORD
