Metadata-Version: 2.1
Name: img-prediction
Version: 0.0.6
Summary: Predict the location of the instance in the picture and Mosaic it
Author: LiuZhiwei
Author-email: 1129459766@qq.com
License: MIT
Classifier: Intended Audience :: Developers
Classifier: License :: OSI Approved :: MIT License
Classifier: Programming Language :: Python :: 3.6
Classifier: Programming Language :: Python :: 3.7
Classifier: Programming Language :: Python :: 3.8
Classifier: Programming Language :: Python :: 3.9
Classifier: Programming Language :: Python :: 3.10
License-File: LICENSE
Requires-Dist: torch (==2.0.1)
Requires-Dist: torchvision (==0.15.2)
Requires-Dist: loguru (==0.7.0)
Requires-Dist: urllib3 (==1.26.6)
